winning/lattice.py
winning/lattice_calibration.py
winning/lattice_conventions.py
winning/lattice_copula.py
winning/lattice_plot.py
winning/lattice_simulation.py
winning/normaldist.py
winning/pandas_util.py
winning/scipyinclusion.py
winning/skew_calibration.py
winning/std_calibration.py
winning-1.0.3.dist-info/LICENSE
winning-1.0.3.dist-info/METADATA
winning-1.0.3.dist-info/WHEEL
winning-1.0.3.dist-info/entry_points.txt
winning-1.0.3.dist-info/top_level.txt
winning-1.0.3.dist-info/RECORD
