Metadata-Version: 2.1
Name: winning
Version: 1.0.3
Summary: Fast ability inference from contest winning probabilities
Home-page: https://github.com/microprediction/winning
Author: microprediction
Author-email: peter.cotton@microprediction.com
License: MIT
Classifier: License :: OSI Approved :: MIT License
Classifier: Programming Language :: Python :: 3
Classifier: Programming Language :: Python :: 3.7
Classifier: Programming Language :: Python :: 3.9
License-File: LICENSE
Requires-Dist: numpy
Requires-Dist: pytest
Requires-Dist: pathlib
Requires-Dist: wheel
